gdbplugins/__init__.py
gdbplugins/clang_support.py
gdbplugins/deploy.py
gdbplugins/gdbinit
gdbplugins/gdbplugins_loader.py
gdbplugins/python.py
gdbplugins/ruby.py
gdbplugins-0.2.dist-info/entry_points.txt
gdbplugins-0.2.dist-info/METADATA
gdbplugins-0.2.dist-info/LICENSE
gdbplugins-0.2.dist-info/WHEEL
gdbplugins-0.2.dist-info/RECORD
