Metadata-Version: 2.1
Name: gdbplugins
Version: 0.2
Summary: Python plugins for gdb making debugging various languages with gdb easy.
License: GNU General Public License v3 (GPLv3) (GNU GPL3)
Author: Jaroslav Henner
Requires-Python: >=3.10,<4.0
Classifier: License :: Other/Proprietary License
Classifier: Programming Language :: Python :: 3
Classifier: Programming Language :: Python :: 3.10
Classifier: Programming Language :: Python :: 3.11
